[
  {
    "start": "2025-03-26T12:00:00",
    "end": "2025-03-26T14:00:00",
    "title": "Telefonie RO gr. 3/3",
    "location": "UTCN - ETTI Observatorului 2 - Sala 509",
    "description": "",
    "source": "ea71e1a3"
  },
  {
    "start": "2025-03-26T08:00:00",
    "end": "2025-03-26T10:00:00",
    "title": "Telefonie RO gr. 3/2",
    "location": "UTCN - ETTI Observatorului 2 - Sala 509",
    "description": "",
    "source": "ea71e1a3"
  },
  {
    "start": "2025-03-24T16:00:00",
    "end": "2025-03-24T20:00:00",
    "title": "TACCFD - TM Mas",
    "location": "UTCN - ETTI Observatorului 2 - Sala 509",
    "description": "",
    "source": "ea71e1a3"
  },
  {
    "start": "2025-01-29T16:35:56",
    "end": "2025-01-29T17:15:00",
    "title": "Reserved",
    "location": "",
    "description": "\n\n\n________________________________________________________________________________\nMicrosoft Teams Need help?<https://aka.ms/JoinTeamsMeeting?omkt=en-US>\nJoin the meeting now<https://teams.microsoft.com/l/meetup-join/19%3ameeting_YjJkZjIyZDctYmFiNC00ZWE1LTgzODEtZDQ5NGU4ZWRhOGRl%40thread.v2/0?context=%7b%22Tid%22%3a%22a6eb79fa-c4a9-4cce-818d-b85274d15305%22%2c%22Oid%22%3a%22c1ee760c-c5d1-4829-8eae-898643add807%22%7d>\nMeeting ID: 377 305 706 355\nPasscode: j3f5CF3D\n________________________________\nDial in by phone\n+40 21 529 2227,,524024208#<tel:+40215292227,,524024208#> Romania, Bucharest\nFind a local number<https://dialin.teams.microsoft.com/31ffe0f8-1aa7-4b50-8338-1559dd2042f9?id=524024208>\nPhone conference ID: 524 024 208#\nFor organizers: Meeting options<https://teams.microsoft.com/meetingOptions/?organizerId=c1ee760c-c5d1-4829-8eae-898643add807&tenantId=a6eb79fa-c4a9-4cce-818d-b85274d15305&threadId=19_meeting_YjJkZjIyZDctYmFiNC00ZWE1LTgzODEtZDQ5NGU4ZWRhOGRl@thread.v2&messageId=0&language=en-US> | Reset dial-in PIN<https://dialin.teams.microsoft.com/usp/pstnconferencing>\nPrivacy and security<https://www.utcluj.ro>\n________________________________________________________________________________\n",
    "source": "ea71e1a3"
  },
  {
    "start": "2025-03-26T10:00:00",
    "end": "2025-03-26T12:00:00",
    "title": "Telefonie RO gr. 3/1",
    "location": "UTCN - ETTI Observatorului 2 - Sala 509",
    "description": "",
    "source": "ea71e1a3"
  },
  {
    "start": "2025-03-18T13:00:00",
    "end": "2025-03-18T14:00:00",
    "title": "Ecosistem Video Yealink - eUT4ALL - e-PNRR",
    "location": "Microsoft Teams Meeting; UTCN - AC Bar - Sala 356; UTCN - IIRMP Muncii 103-105 - Sala M310; UTCN - AC Bar - Sala 26B; UTCN - Cons Observatorului 72-74 - Sala O1; UTCN - AC Bar - Sala 16B; UTCN - AC Bar - Sala BT 604; UTCN - ICIA - Observatorului - Sala 28",
    "description": "",
    "source": "ea71e1a3"
  },
  {
    "start": "2025-03-25T16:00:00",
    "end": "2025-03-25T20:00:00",
    "title": "BTDDBR - TC Mas",
    "location": "UTCN - ETTI Observatorului 2 - Sala 509",
    "description": "",
    "source": "ea71e1a3"
  },
  {
    "start": "2025-03-10T07:37:21",
    "end": "2025-03-10T07:45:00",
    "title": "Reserved",
    "location": "",
    "description": "\n\n\n________________________________________________________________________________\nMicrosoft Teams Need help?<https://aka.ms/JoinTeamsMeeting?omkt=en-US>\nJoin the meeting now<https://teams.microsoft.com/l/meetup-join/19%3ameeting_MzEwMzA5OTctYzFjYS00Njc2LTlmNGYtYTQxMWExNTdkYzQy%40thread.v2/0?context=%7b%22Tid%22%3a%22a6eb79fa-c4a9-4cce-818d-b85274d15305%22%2c%22Oid%22%3a%22c1ee760c-c5d1-4829-8eae-898643add807%22%7d>\nMeeting ID: 330 527 864 629\nPasscode: 95KP2Vz3\n________________________________\nDial in by phone\n+40 21 529 2227,,208547143#<tel:+40215292227,,208547143#> Romania, Bucharest\nFind a local number<https://dialin.teams.microsoft.com/31ffe0f8-1aa7-4b50-8338-1559dd2042f9?id=208547143>\nPhone conference ID: 208 547 143#\nFor organizers: Meeting options<https://teams.microsoft.com/meetingOptions/?organizerId=c1ee760c-c5d1-4829-8eae-898643add807&tenantId=a6eb79fa-c4a9-4cce-818d-b85274d15305&threadId=19_meeting_MzEwMzA5OTctYzFjYS00Njc2LTlmNGYtYTQxMWExNTdkYzQy@thread.v2&messageId=0&language=en-US> | Reset dial-in PIN<https://dialin.teams.microsoft.com/usp/pstnconferencing>\nPrivacy and security<https://www.utcluj.ro>\n________________________________________________________________________________\n",
    "source": "ea71e1a3"
  },
  {
    "start": "2025-01-29T11:15:53",
    "end": "2025-01-29T11:30:00",
    "title": "Reserved",
    "location": "",
    "description": "\n\n\n________________________________________________________________________________\nMicrosoft Teams Need help?<https://aka.ms/JoinTeamsMeeting?omkt=en-US>\nJoin the meeting now<https://teams.microsoft.com/l/meetup-join/19%3ameeting_M2IxYjE3MzQtMjBiZS00NWMyLThkNGItZGMyZTA2YmFlODgx%40thread.v2/0?context=%7b%22Tid%22%3a%22a6eb79fa-c4a9-4cce-818d-b85274d15305%22%2c%22Oid%22%3a%22c1ee760c-c5d1-4829-8eae-898643add807%22%7d>\nMeeting ID: 337 783 179 102\nPasscode: Yh9Dv7Jv\n________________________________\nDial in by phone\n+40 21 529 2227,,191467279#<tel:+40215292227,,191467279#> Romania, Bucharest\nFind a local number<https://dialin.teams.microsoft.com/31ffe0f8-1aa7-4b50-8338-1559dd2042f9?id=191467279>\nPhone conference ID: 191 467 279#\nFor organizers: Meeting options<https://teams.microsoft.com/meetingOptions/?organizerId=c1ee760c-c5d1-4829-8eae-898643add807&tenantId=a6eb79fa-c4a9-4cce-818d-b85274d15305&threadId=19_meeting_M2IxYjE3MzQtMjBiZS00NWMyLThkNGItZGMyZTA2YmFlODgx@thread.v2&messageId=0&language=en-US> | Reset dial-in PIN<https://dialin.teams.microsoft.com/usp/pstnconferencing>\nPrivacy and security<https://www.utcluj.ro>\n________________________________________________________________________________\n",
    "source": "ea71e1a3"
  },
  {
    "start": "2025-03-26T16:00:00",
    "end": "2025-03-26T18:00:00",
    "title": "Telefonie ENG gr. 1/3",
    "location": "UTCN - ETTI Observatorului 2 - Sala 509",
    "description": "",
    "source": "ea71e1a3"
  },
  {
    "start": "2025-02-27T12:56:18",
    "end": "2025-02-27T14:45:00",
    "title": "Reserved",
    "location": "",
    "description": "\n\n\n________________________________________________________________________________\nMicrosoft Teams Need help?<https://aka.ms/JoinTeamsMeeting?omkt=en-US>\nJoin the meeting now<https://teams.microsoft.com/l/meetup-join/19%3ameeting_NWY5YzM5MmUtNmZiNC00MDk0LWJmNTYtZWJiZmNhZTNlMzMx%40thread.v2/0?context=%7b%22Tid%22%3a%22a6eb79fa-c4a9-4cce-818d-b85274d15305%22%2c%22Oid%22%3a%22c1ee760c-c5d1-4829-8eae-898643add807%22%7d>\nMeeting ID: 365 781 976 884\nPasscode: o37ZM3sp\n________________________________\nDial in by phone\n+40 21 529 2227,,192218778#<tel:+40215292227,,192218778#> Romania, Bucharest\nFind a local number<https://dialin.teams.microsoft.com/31ffe0f8-1aa7-4b50-8338-1559dd2042f9?id=192218778>\nPhone conference ID: 192 218 778#\nFor organizers: Meeting options<https://teams.microsoft.com/meetingOptions/?organizerId=c1ee760c-c5d1-4829-8eae-898643add807&tenantId=a6eb79fa-c4a9-4cce-818d-b85274d15305&threadId=19_meeting_NWY5YzM5MmUtNmZiNC00MDk0LWJmNTYtZWJiZmNhZTNlMzMx@thread.v2&messageId=0&language=en-US> | Reset dial-in PIN<https://dialin.teams.microsoft.com/usp/pstnconferencing>\nPrivacy and security<https://www.utcluj.ro>\n________________________________________________________________________________\n",
    "source": "ea71e1a3"
  },
  {
    "start": "2025-03-27T12:00:00",
    "end": "2025-03-27T14:00:00",
    "title": "Telefonie RO gr. 1/2",
    "location": "UTCN - ETTI Observatorului 2 - Sala 509",
    "description": "",
    "source": "ea71e1a3"
  },
  {
    "start": "2025-03-26T14:00:00",
    "end": "2025-03-26T16:00:00",
    "title": "Telefonie ENG gr. 1/2",
    "location": "UTCN - ETTI Observatorului 2 - Sala 509",
    "description": "",
    "source": "ea71e1a3"
  },
  {
    "start": "2025-03-27T16:00:00",
    "end": "2025-03-27T18:00:00",
    "title": "Telefonie RO gr. 1/1",
    "location": "UTCN - ETTI Observatorului 2 - Sala 509",
    "description": "",
    "source": "ea71e1a3"
  },
  {
    "start": "2025-03-27T14:00:00",
    "end": "2025-03-27T16:00:00",
    "title": "Telefonie RO gr. 1/1",
    "location": "UTCN - ETTI Observatorului 2 - Sala 509",
    "description": "",
    "source": "ea71e1a3"
  },
  {
    "start": "2025-03-27T18:00:00",
    "end": "2025-03-27T20:00:00",
    "title": "Telefonie RO gr. 2/2",
    "location": "UTCN - ETTI Observatorului 2 - Sala 509",
    "description": "",
    "source": "ea71e1a3"
  },
  {
    "start": "2025-03-28T08:00:00",
    "end": "2025-03-28T10:00:00",
    "title": "Telefonie ENG gr. 1/1",
    "location": "UTCN - ETTI Observatorului 2 - Sala 509",
    "description": "",
    "source": "ea71e1a3"
  }
]