[
  {
    "start": "2025-12-29T10:00:00+02:00",
    "end": "2025-12-29T16:00:00+02:00",
    "title": "Radiocomunicații Celulare (l)",
    "location": "UTCN - ETTI Observatorului 2 - Sala 410 (RO)",
    "raw": {
      "__type": "CalendarItem:#Exchange",
      "ItemId": {
        "__type": "ItemId:#Exchange",
        "ChangeKey": "DwAAABYAAACHeWQkFedHR7fG98QQLjwkAAC1lNis",
        "Id": "AAMkAGZmMTBkNmYwLTJjNjktNDE1NS05ZTA0LWM2NmVmNmM2NjIzNQFRAAgI3kZtNbrAAEYAAAAANWPAfxC+aEybfSTRtwpRxgcAh3lkJBXnR0e3xvfEEC48JAAAAAABDQAAh3lkJBXnR0e3xvfEEC48JAAAtXobvAAAEA=="
      },
      "ParentFolderId": {
        "__type": "FolderId:#Exchange",
        "Id": "AAMkAGZmMTBkNmYwLTJjNjktNDE1NS05ZTA0LWM2NmVmNmM2NjIzNQAuAAAAAAA1Y8B/EL5oTJt9JNG3ClHGAQCHeWQkFedHR7fG98QQLjwkAAAAAAENAAA=",
        "ChangeKey": "AQAAAA=="
      },
      "Start": "2025-12-29T10:00:00+02:00",
      "End": "2025-12-29T16:00:00+02:00",
      "Subject": "Radiocomunicații Celulare (L) - an IV TST-RO",
      "Sensitivity": "Normal",
      "FreeBusyType": "Busy",
      "CalendarItemType": "Occurrence",
      "Location": {
        "DisplayName": "UTCN - ETTI Observatorului 2 - Sala 410 (RO)",
        "PostalAddress": {
          "Street": null,
          "City": null,
          "State": null,
          "Country": null,
          "PostalCode": null,
          "PostOfficeBox": null,
          "Type": "Home",
          "LocationSource": "None"
        },
        "IdType": "Unknown",
        "LocationType": "Unknown"
      },
      "Charm": "None"
    },
    "source": "8813d675",
    "color": "#20c997"
  },
  {
    "start": "2025-12-30T08:00:00+02:00",
    "end": "2025-12-30T14:00:00+02:00",
    "title": "Sisteme De Comunicații (l)",
    "location": "UTCN - ETTI Observatorului 2 - Sala 410 (RO)",
    "raw": {
      "__type": "CalendarItem:#Exchange",
      "ItemId": {
        "__type": "ItemId:#Exchange",
        "ChangeKey": "DwAAABYAAACHeWQkFedHR7fG98QQLjwkAAC1lNim",
        "Id": "AAMkAGZmMTBkNmYwLTJjNjktNDE1NS05ZTA0LWM2NmVmNmM2NjIzNQFRAAgI3kc2YCSAAEYAAAAANWPAfxC+aEybfSTRtwpRxgcAh3lkJBXnR0e3xvfEEC48JAAAAAABDQAAh3lkJBXnR0e3xvfEEC48JAAAtXobuwAAEA=="
      },
      "ParentFolderId": {
        "__type": "FolderId:#Exchange",
        "Id": "AAMkAGZmMTBkNmYwLTJjNjktNDE1NS05ZTA0LWM2NmVmNmM2NjIzNQAuAAAAAAA1Y8B/EL5oTJt9JNG3ClHGAQCHeWQkFedHR7fG98QQLjwkAAAAAAENAAA=",
        "ChangeKey": "AQAAAA=="
      },
      "Start": "2025-12-30T08:00:00+02:00",
      "End": "2025-12-30T14:00:00+02:00",
      "Subject": "Sisteme de comunicații (L) - an III IEDEEE ",
      "Sensitivity": "Normal",
      "FreeBusyType": "Busy",
      "CalendarItemType": "Occurrence",
      "Location": {
        "DisplayName": "UTCN - ETTI Observatorului 2 - Sala 410 (RO)",
        "PostalAddress": {
          "Street": null,
          "City": null,
          "State": null,
          "Country": null,
          "PostalCode": null,
          "PostOfficeBox": null,
          "Type": "Home",
          "LocationSource": "None"
        },
        "IdType": "Unknown",
        "LocationType": "Unknown"
      },
      "Charm": "None"
    },
    "source": "8813d675",
    "color": "#20c997"
  },
  {
    "start": "2025-12-31T10:00:00+02:00",
    "end": "2025-12-31T12:00:00+02:00",
    "title": "Sisteme De Comunicații",
    "location": "UTCN - ETTI Observatorului 2 - Sala 410 (RO)",
    "raw": {
      "__type": "CalendarItem:#Exchange",
      "ItemId": {
        "__type": "ItemId:#Exchange",
        "ChangeKey": "DwAAABYAAACHeWQkFedHR7fG98QQLjwkAAC1lNi0",
        "Id": "AAMkAGZmMTBkNmYwLTJjNjktNDE1NS05ZTA0LWM2NmVmNmM2NjIzNQFRAAgI3kf/io5AAEYAAAAANWPAfxC+aEybfSTRtwpRxgcAh3lkJBXnR0e3xvfEEC48JAAAAAABDQAAh3lkJBXnR0e3xvfEEC48JAAAtXobvgAAEA=="
      },
      "ParentFolderId": {
        "__type": "FolderId:#Exchange",
        "Id": "AAMkAGZmMTBkNmYwLTJjNjktNDE1NS05ZTA0LWM2NmVmNmM2NjIzNQAuAAAAAAA1Y8B/EL5oTJt9JNG3ClHGAQCHeWQkFedHR7fG98QQLjwkAAAAAAENAAA=",
        "ChangeKey": "AQAAAA=="
      },
      "Start": "2025-12-31T10:00:00+02:00",
      "End": "2025-12-31T12:00:00+02:00",
      "Subject": "Sisteme de comunicații (P) - an III IEDEEE",
      "Sensitivity": "Normal",
      "FreeBusyType": "Busy",
      "CalendarItemType": "Occurrence",
      "Location": {
        "DisplayName": "UTCN - ETTI Observatorului 2 - Sala 410 (RO)",
        "PostalAddress": {
          "Street": null,
          "City": null,
          "State": null,
          "Country": null,
          "PostalCode": null,
          "PostOfficeBox": null,
          "Type": "Home",
          "LocationSource": "None"
        },
        "IdType": "Unknown",
        "LocationType": "Unknown"
      },
      "Charm": "None"
    },
    "source": "8813d675",
    "color": "#20c997"
  },
  {
    "start": "2025-12-31T17:00:00+02:00",
    "end": "2025-12-31T19:00:00+02:00",
    "title": "Proiectarea Rețelelor Radio",
    "location": "UTCN - ETTI Observatorului 2 - Sala 410 (RO)",
    "raw": {
      "__type": "CalendarItem:#Exchange",
      "ItemId": {
        "__type": "ItemId:#Exchange",
        "ChangeKey": "DwAAABYAAACHeWQkFedHR7fG98QQLjwkAAC1lNjs",
        "Id": "AAMkAGZmMTBkNmYwLTJjNjktNDE1NS05ZTA0LWM2NmVmNmM2NjIzNQFRAAgI3kf/io5AAEYAAAAANWPAfxC+aEybfSTRtwpRxgcAh3lkJBXnR0e3xvfEEC48JAAAAAABDQAAh3lkJBXnR0e3xvfEEC48JAAAtXobwwAAEA=="
      },
      "ParentFolderId": {
        "__type": "FolderId:#Exchange",
        "Id": "AAMkAGZmMTBkNmYwLTJjNjktNDE1NS05ZTA0LWM2NmVmNmM2NjIzNQAuAAAAAAA1Y8B/EL5oTJt9JNG3ClHGAQCHeWQkFedHR7fG98QQLjwkAAAAAAENAAA=",
        "ChangeKey": "AQAAAA=="
      },
      "Start": "2025-12-31T17:00:00+02:00",
      "End": "2025-12-31T19:00:00+02:00",
      "Subject": "Proiectarea rețelelor radio - TC II",
      "Sensitivity": "Normal",
      "FreeBusyType": "Busy",
      "CalendarItemType": "Occurrence",
      "Location": {
        "DisplayName": "UTCN - ETTI Observatorului 2 - Sala 410 (RO)",
        "PostalAddress": {
          "Street": null,
          "City": null,
          "State": null,
          "Country": null,
          "PostalCode": null,
          "PostOfficeBox": null,
          "Type": "Home",
          "LocationSource": "None"
        },
        "IdType": "Unknown",
        "LocationType": "Unknown"
      },
      "Charm": "None"
    },
    "source": "8813d675",
    "color": "#20c997"
  },
  {
    "start": "2026-01-01T10:00:00+02:00",
    "end": "2026-01-01T14:00:00+02:00",
    "title": "Cellular Radiocommunications",
    "location": "UTCN - ETTI Observatorului 2 - Sala 410 (RO)",
    "raw": {
      "__type": "CalendarItem:#Exchange",
      "ItemId": {
        "__type": "ItemId:#Exchange",
        "ChangeKey": "DwAAABYAAACHeWQkFedHR7fG98QQLjwkAAC1lNi/",
        "Id": "AAMkAGZmMTBkNmYwLTJjNjktNDE1NS05ZTA0LWM2NmVmNmM2NjIzNQFRAAgI3kjItPgAAEYAAAAANWPAfxC+aEybfSTRtwpRxgcAh3lkJBXnR0e3xvfEEC48JAAAAAABDQAAh3lkJBXnR0e3xvfEEC48JAAAtXobvwAAEA=="
      },
      "ParentFolderId": {
        "__type": "FolderId:#Exchange",
        "Id": "AAMkAGZmMTBkNmYwLTJjNjktNDE1NS05ZTA0LWM2NmVmNmM2NjIzNQAuAAAAAAA1Y8B/EL5oTJt9JNG3ClHGAQCHeWQkFedHR7fG98QQLjwkAAAAAAENAAA=",
        "ChangeKey": "AQAAAA=="
      },
      "Start": "2026-01-01T10:00:00+02:00",
      "End": "2026-01-01T14:00:00+02:00",
      "Subject": "Cellular Radiocommunications - IV TST-ENG",
      "Sensitivity": "Normal",
      "FreeBusyType": "Busy",
      "CalendarItemType": "Occurrence",
      "Location": {
        "DisplayName": "UTCN - ETTI Observatorului 2 - Sala 410 (RO)",
        "PostalAddress": {
          "Street": null,
          "City": null,
          "State": null,
          "Country": null,
          "PostalCode": null,
          "PostOfficeBox": null,
          "Type": "Home",
          "LocationSource": "None"
        },
        "IdType": "Unknown",
        "LocationType": "Unknown"
      },
      "Charm": "None"
    },
    "source": "8813d675",
    "color": "#20c997"
  },
  {
    "start": "2026-01-01T14:00:00+02:00",
    "end": "2026-01-01T16:00:00+02:00",
    "title": "Iot Project",
    "location": "UTCN - ETTI Observatorului 2 - Sala 410 (RO)",
    "raw": {
      "__type": "CalendarItem:#Exchange",
      "ItemId": {
        "__type": "ItemId:#Exchange",
        "ChangeKey": "DwAAABYAAACHeWQkFedHR7fG98QQLjwkAAC1lNjH",
        "Id": "AAMkAGZmMTBkNmYwLTJjNjktNDE1NS05ZTA0LWM2NmVmNmM2NjIzNQFRAAgI3kjItPgAAEYAAAAANWPAfxC+aEybfSTRtwpRxgcAh3lkJBXnR0e3xvfEEC48JAAAAAABDQAAh3lkJBXnR0e3xvfEEC48JAAAtXobwAAAEA=="
      },
      "ParentFolderId": {
        "__type": "FolderId:#Exchange",
        "Id": "AAMkAGZmMTBkNmYwLTJjNjktNDE1NS05ZTA0LWM2NmVmNmM2NjIzNQAuAAAAAAA1Y8B/EL5oTJt9JNG3ClHGAQCHeWQkFedHR7fG98QQLjwkAAAAAAENAAA=",
        "ChangeKey": "AQAAAA=="
      },
      "Start": "2026-01-01T14:00:00+02:00",
      "End": "2026-01-01T16:00:00+02:00",
      "Subject": "IoT Project - IV TST-ENG",
      "Sensitivity": "Normal",
      "FreeBusyType": "Busy",
      "CalendarItemType": "Occurrence",
      "Location": {
        "DisplayName": "UTCN - ETTI Observatorului 2 - Sala 410 (RO)",
        "PostalAddress": {
          "Street": null,
          "City": null,
          "State": null,
          "Country": null,
          "PostalCode": null,
          "PostOfficeBox": null,
          "Type": "Home",
          "LocationSource": "None"
        },
        "IdType": "Unknown",
        "LocationType": "Unknown"
      },
      "Charm": "None"
    },
    "source": "8813d675",
    "color": "#20c997"
  },
  {
    "start": "2026-01-01T16:00:00+02:00",
    "end": "2026-01-01T18:00:00+02:00",
    "title": "Sisteme Wireless",
    "location": "UTCN - ETTI Observatorului 2 - Sala 410 (RO)",
    "raw": {
      "__type": "CalendarItem:#Exchange",
      "ItemId": {
        "__type": "ItemId:#Exchange",
        "ChangeKey": "DwAAABYAAACHeWQkFedHR7fG98QQLjwkAAC1lNjQ",
        "Id": "AAMkAGZmMTBkNmYwLTJjNjktNDE1NS05ZTA0LWM2NmVmNmM2NjIzNQFRAAgI3kjItPgAAEYAAAAANWPAfxC+aEybfSTRtwpRxgcAh3lkJBXnR0e3xvfEEC48JAAAAAABDQAAh3lkJBXnR0e3xvfEEC48JAAAtXobwQAAEA=="
      },
      "ParentFolderId": {
        "__type": "FolderId:#Exchange",
        "Id": "AAMkAGZmMTBkNmYwLTJjNjktNDE1NS05ZTA0LWM2NmVmNmM2NjIzNQAuAAAAAAA1Y8B/EL5oTJt9JNG3ClHGAQCHeWQkFedHR7fG98QQLjwkAAAAAAENAAA=",
        "ChangeKey": "AQAAAA=="
      },
      "Start": "2026-01-01T16:00:00+02:00",
      "End": "2026-01-01T18:00:00+02:00",
      "Subject": "Sisteme Wireless - TC I",
      "Sensitivity": "Normal",
      "FreeBusyType": "Busy",
      "CalendarItemType": "Occurrence",
      "Location": {
        "DisplayName": "UTCN - ETTI Observatorului 2 - Sala 410 (RO)",
        "PostalAddress": {
          "Street": null,
          "City": null,
          "State": null,
          "Country": null,
          "PostalCode": null,
          "PostOfficeBox": null,
          "Type": "Home",
          "LocationSource": "None"
        },
        "IdType": "Unknown",
        "LocationType": "Unknown"
      },
      "Charm": "None"
    },
    "source": "8813d675",
    "color": "#20c997"
  },
  {
    "start": "2026-01-01T18:00:00+02:00",
    "end": "2026-01-01T19:00:00+02:00",
    "title": "Proiect Cercetare",
    "location": "",
    "raw": {
      "__type": "CalendarItem:#Exchange",
      "ItemId": {
        "__type": "ItemId:#Exchange",
        "ChangeKey": "DwAAABYAAACHeWQkFedHR7fG98QQLjwkAAC1lNjX",
        "Id": "AAMkAGZmMTBkNmYwLTJjNjktNDE1NS05ZTA0LWM2NmVmNmM2NjIzNQFRAAgI3kjItPgAAEYAAAAANWPAfxC+aEybfSTRtwpRxgcAh3lkJBXnR0e3xvfEEC48JAAAAAABDQAAh3lkJBXnR0e3xvfEEC48JAAAtXobwgAAEA=="
      },
      "ParentFolderId": {
        "__type": "FolderId:#Exchange",
        "Id": "AAMkAGZmMTBkNmYwLTJjNjktNDE1NS05ZTA0LWM2NmVmNmM2NjIzNQAuAAAAAAA1Y8B/EL5oTJt9JNG3ClHGAQCHeWQkFedHR7fG98QQLjwkAAAAAAENAAA=",
        "ChangeKey": "AQAAAA=="
      },
      "Start": "2026-01-01T18:00:00+02:00",
      "End": "2026-01-01T19:00:00+02:00",
      "Subject": "Proiect cercetare - TC I",
      "Sensitivity": "Normal",
      "FreeBusyType": "Busy",
      "CalendarItemType": "Occurrence",
      "Location": {
        "DisplayName": "",
        "PostalAddress": {
          "Street": null,
          "City": null,
          "State": null,
          "Country": null,
          "PostalCode": null,
          "PostOfficeBox": null,
          "Type": "Home",
          "LocationSource": "None"
        },
        "IdType": "Unknown",
        "LocationType": "Unknown"
      },
      "Charm": "None"
    },
    "source": "8813d675",
    "color": "#20c997"
  },
  {
    "start": "2026-01-05T10:00:00+02:00",
    "end": "2026-01-05T16:00:00+02:00",
    "title": "Radiocomunicații Celulare (l)",
    "location": "UTCN - ETTI Observatorului 2 - Sala 410 (RO)",
    "raw": {
      "__type": "CalendarItem:#Exchange",
      "ItemId": {
        "__type": "ItemId:#Exchange",
        "ChangeKey": "DwAAABYAAACHeWQkFedHR7fG98QQLjwkAAC1lNis",
        "Id": "AAMkAGZmMTBkNmYwLTJjNjktNDE1NS05ZTA0LWM2NmVmNmM2NjIzNQFRAAgI3kvtXp8AAEYAAAAANWPAfxC+aEybfSTRtwpRxgcAh3lkJBXnR0e3xvfEEC48JAAAAAABDQAAh3lkJBXnR0e3xvfEEC48JAAAtXobvAAAEA=="
      },
      "ParentFolderId": {
        "__type": "FolderId:#Exchange",
        "Id": "AAMkAGZmMTBkNmYwLTJjNjktNDE1NS05ZTA0LWM2NmVmNmM2NjIzNQAuAAAAAAA1Y8B/EL5oTJt9JNG3ClHGAQCHeWQkFedHR7fG98QQLjwkAAAAAAENAAA=",
        "ChangeKey": "AQAAAA=="
      },
      "Start": "2026-01-05T10:00:00+02:00",
      "End": "2026-01-05T16:00:00+02:00",
      "Subject": "Radiocomunicații Celulare (L) - an IV TST-RO",
      "Sensitivity": "Normal",
      "FreeBusyType": "Busy",
      "CalendarItemType": "Occurrence",
      "Location": {
        "DisplayName": "UTCN - ETTI Observatorului 2 - Sala 410 (RO)",
        "PostalAddress": {
          "Street": null,
          "City": null,
          "State": null,
          "Country": null,
          "PostalCode": null,
          "PostOfficeBox": null,
          "Type": "Home",
          "LocationSource": "None"
        },
        "IdType": "Unknown",
        "LocationType": "Unknown"
      },
      "Charm": "None"
    },
    "source": "8813d675",
    "color": "#20c997"
  },
  {
    "start": "2026-01-06T08:00:00+02:00",
    "end": "2026-01-06T14:00:00+02:00",
    "title": "Sisteme De Comunicații (l)",
    "location": "UTCN - ETTI Observatorului 2 - Sala 410 (RO)",
    "raw": {
      "__type": "CalendarItem:#Exchange",
      "ItemId": {
        "__type": "ItemId:#Exchange",
        "ChangeKey": "DwAAABYAAACHeWQkFedHR7fG98QQLjwkAAC1lNim",
        "Id": "AAMkAGZmMTBkNmYwLTJjNjktNDE1NS05ZTA0LWM2NmVmNmM2NjIzNQFRAAgI3ky2iQjAAEYAAAAANWPAfxC+aEybfSTRtwpRxgcAh3lkJBXnR0e3xvfEEC48JAAAAAABDQAAh3lkJBXnR0e3xvfEEC48JAAAtXobuwAAEA=="
      },
      "ParentFolderId": {
        "__type": "FolderId:#Exchange",
        "Id": "AAMkAGZmMTBkNmYwLTJjNjktNDE1NS05ZTA0LWM2NmVmNmM2NjIzNQAuAAAAAAA1Y8B/EL5oTJt9JNG3ClHGAQCHeWQkFedHR7fG98QQLjwkAAAAAAENAAA=",
        "ChangeKey": "AQAAAA=="
      },
      "Start": "2026-01-06T08:00:00+02:00",
      "End": "2026-01-06T14:00:00+02:00",
      "Subject": "Sisteme de comunicații (L) - an III IEDEEE ",
      "Sensitivity": "Normal",
      "FreeBusyType": "Busy",
      "CalendarItemType": "Occurrence",
      "Location": {
        "DisplayName": "UTCN - ETTI Observatorului 2 - Sala 410 (RO)",
        "PostalAddress": {
          "Street": null,
          "City": null,
          "State": null,
          "Country": null,
          "PostalCode": null,
          "PostOfficeBox": null,
          "Type": "Home",
          "LocationSource": "None"
        },
        "IdType": "Unknown",
        "LocationType": "Unknown"
      },
      "Charm": "None"
    },
    "source": "8813d675",
    "color": "#20c997"
  },
  {
    "start": "2026-01-07T08:00:00+02:00",
    "end": "2026-01-07T12:00:00+02:00",
    "title": "Sisteme De Comunicații",
    "location": "UTCN - ETTI Observatorului 2 - Sala 410 (RO)",
    "raw": {
      "__type": "CalendarItem:#Exchange",
      "ItemId": {
        "__type": "ItemId:#Exchange",
        "ChangeKey": "DwAAABYAAACHeWQkFedHR7fG98QQLjwkAAC1lNie",
        "Id": "AAMkAGZmMTBkNmYwLTJjNjktNDE1NS05ZTA0LWM2NmVmNmM2NjIzNQFRAAgI3k1/s3KAAEYAAAAANWPAfxC+aEybfSTRtwpRxgcAh3lkJBXnR0e3xvfEEC48JAAAAAABDQAAh3lkJBXnR0e3xvfEEC48JAAAtXobvQAAEA=="
      },
      "ParentFolderId": {
        "__type": "FolderId:#Exchange",
        "Id": "AAMkAGZmMTBkNmYwLTJjNjktNDE1NS05ZTA0LWM2NmVmNmM2NjIzNQAuAAAAAAA1Y8B/EL5oTJt9JNG3ClHGAQCHeWQkFedHR7fG98QQLjwkAAAAAAENAAA=",
        "ChangeKey": "AQAAAA=="
      },
      "Start": "2026-01-07T08:00:00+02:00",
      "End": "2026-01-07T12:00:00+02:00",
      "Subject": "Sisteme de comunicații (P) - an III IEDEEE",
      "Sensitivity": "Normal",
      "FreeBusyType": "Busy",
      "CalendarItemType": "Occurrence",
      "Location": {
        "DisplayName": "UTCN - ETTI Observatorului 2 - Sala 410 (RO)",
        "PostalAddress": {
          "Street": null,
          "City": null,
          "State": null,
          "Country": null,
          "PostalCode": null,
          "PostOfficeBox": null,
          "Type": "Home",
          "LocationSource": "None"
        },
        "IdType": "Unknown",
        "LocationType": "Unknown"
      },
      "Charm": "None"
    },
    "source": "8813d675",
    "color": "#20c997"
  },
  {
    "start": "2026-01-07T17:00:00+02:00",
    "end": "2026-01-07T19:00:00+02:00",
    "title": "Proiectarea Rețelelor Radio",
    "location": "UTCN - ETTI Observatorului 2 - Sala 410 (RO)",
    "raw": {
      "__type": "CalendarItem:#Exchange",
      "ItemId": {
        "__type": "ItemId:#Exchange",
        "ChangeKey": "DwAAABYAAACHeWQkFedHR7fG98QQLjwkAAC1lNjs",
        "Id": "AAMkAGZmMTBkNmYwLTJjNjktNDE1NS05ZTA0LWM2NmVmNmM2NjIzNQFRAAgI3k1/s3KAAEYAAAAANWPAfxC+aEybfSTRtwpRxgcAh3lkJBXnR0e3xvfEEC48JAAAAAABDQAAh3lkJBXnR0e3xvfEEC48JAAAtXobwwAAEA=="
      },
      "ParentFolderId": {
        "__type": "FolderId:#Exchange",
        "Id": "AAMkAGZmMTBkNmYwLTJjNjktNDE1NS05ZTA0LWM2NmVmNmM2NjIzNQAuAAAAAAA1Y8B/EL5oTJt9JNG3ClHGAQCHeWQkFedHR7fG98QQLjwkAAAAAAENAAA=",
        "ChangeKey": "AQAAAA=="
      },
      "Start": "2026-01-07T17:00:00+02:00",
      "End": "2026-01-07T19:00:00+02:00",
      "Subject": "Proiectarea rețelelor radio - TC II",
      "Sensitivity": "Normal",
      "FreeBusyType": "Busy",
      "CalendarItemType": "Occurrence",
      "Location": {
        "DisplayName": "UTCN - ETTI Observatorului 2 - Sala 410 (RO)",
        "PostalAddress": {
          "Street": null,
          "City": null,
          "State": null,
          "Country": null,
          "PostalCode": null,
          "PostOfficeBox": null,
          "Type": "Home",
          "LocationSource": "None"
        },
        "IdType": "Unknown",
        "LocationType": "Unknown"
      },
      "Charm": "None"
    },
    "source": "8813d675",
    "color": "#20c997"
  },
  {
    "start": "2026-01-08T10:00:00+02:00",
    "end": "2026-01-08T14:00:00+02:00",
    "title": "Cellular Radiocommunications",
    "location": "UTCN - ETTI Observatorului 2 - Sala 410 (RO)",
    "raw": {
      "__type": "CalendarItem:#Exchange",
      "ItemId": {
        "__type": "ItemId:#Exchange",
        "ChangeKey": "DwAAABYAAACHeWQkFedHR7fG98QQLjwkAAC1lNi/",
        "Id": "AAMkAGZmMTBkNmYwLTJjNjktNDE1NS05ZTA0LWM2NmVmNmM2NjIzNQFRAAgI3k5I3dxAAEYAAAAANWPAfxC+aEybfSTRtwpRxgcAh3lkJBXnR0e3xvfEEC48JAAAAAABDQAAh3lkJBXnR0e3xvfEEC48JAAAtXobvwAAEA=="
      },
      "ParentFolderId": {
        "__type": "FolderId:#Exchange",
        "Id": "AAMkAGZmMTBkNmYwLTJjNjktNDE1NS05ZTA0LWM2NmVmNmM2NjIzNQAuAAAAAAA1Y8B/EL5oTJt9JNG3ClHGAQCHeWQkFedHR7fG98QQLjwkAAAAAAENAAA=",
        "ChangeKey": "AQAAAA=="
      },
      "Start": "2026-01-08T10:00:00+02:00",
      "End": "2026-01-08T14:00:00+02:00",
      "Subject": "Cellular Radiocommunications - IV TST-ENG",
      "Sensitivity": "Normal",
      "FreeBusyType": "Busy",
      "CalendarItemType": "Occurrence",
      "Location": {
        "DisplayName": "UTCN - ETTI Observatorului 2 - Sala 410 (RO)",
        "PostalAddress": {
          "Street": null,
          "City": null,
          "State": null,
          "Country": null,
          "PostalCode": null,
          "PostOfficeBox": null,
          "Type": "Home",
          "LocationSource": "None"
        },
        "IdType": "Unknown",
        "LocationType": "Unknown"
      },
      "Charm": "None"
    },
    "source": "8813d675",
    "color": "#20c997"
  },
  {
    "start": "2026-01-08T14:00:00+02:00",
    "end": "2026-01-08T16:00:00+02:00",
    "title": "Iot Project",
    "location": "UTCN - ETTI Observatorului 2 - Sala 410 (RO)",
    "raw": {
      "__type": "CalendarItem:#Exchange",
      "ItemId": {
        "__type": "ItemId:#Exchange",
        "ChangeKey": "DwAAABYAAACHeWQkFedHR7fG98QQLjwkAAC1lNjH",
        "Id": "AAMkAGZmMTBkNmYwLTJjNjktNDE1NS05ZTA0LWM2NmVmNmM2NjIzNQFRAAgI3k5I3dxAAEYAAAAANWPAfxC+aEybfSTRtwpRxgcAh3lkJBXnR0e3xvfEEC48JAAAAAABDQAAh3lkJBXnR0e3xvfEEC48JAAAtXobwAAAEA=="
      },
      "ParentFolderId": {
        "__type": "FolderId:#Exchange",
        "Id": "AAMkAGZmMTBkNmYwLTJjNjktNDE1NS05ZTA0LWM2NmVmNmM2NjIzNQAuAAAAAAA1Y8B/EL5oTJt9JNG3ClHGAQCHeWQkFedHR7fG98QQLjwkAAAAAAENAAA=",
        "ChangeKey": "AQAAAA=="
      },
      "Start": "2026-01-08T14:00:00+02:00",
      "End": "2026-01-08T16:00:00+02:00",
      "Subject": "IoT Project - IV TST-ENG",
      "Sensitivity": "Normal",
      "FreeBusyType": "Busy",
      "CalendarItemType": "Occurrence",
      "Location": {
        "DisplayName": "UTCN - ETTI Observatorului 2 - Sala 410 (RO)",
        "PostalAddress": {
          "Street": null,
          "City": null,
          "State": null,
          "Country": null,
          "PostalCode": null,
          "PostOfficeBox": null,
          "Type": "Home",
          "LocationSource": "None"
        },
        "IdType": "Unknown",
        "LocationType": "Unknown"
      },
      "Charm": "None"
    },
    "source": "8813d675",
    "color": "#20c997"
  },
  {
    "start": "2026-01-08T16:00:00+02:00",
    "end": "2026-01-08T18:00:00+02:00",
    "title": "Sisteme Wireless",
    "location": "UTCN - ETTI Observatorului 2 - Sala 410 (RO)",
    "raw": {
      "__type": "CalendarItem:#Exchange",
      "ItemId": {
        "__type": "ItemId:#Exchange",
        "ChangeKey": "DwAAABYAAACHeWQkFedHR7fG98QQLjwkAAC1lNjQ",
        "Id": "AAMkAGZmMTBkNmYwLTJjNjktNDE1NS05ZTA0LWM2NmVmNmM2NjIzNQFRAAgI3k5I3dxAAEYAAAAANWPAfxC+aEybfSTRtwpRxgcAh3lkJBXnR0e3xvfEEC48JAAAAAABDQAAh3lkJBXnR0e3xvfEEC48JAAAtXobwQAAEA=="
      },
      "ParentFolderId": {
        "__type": "FolderId:#Exchange",
        "Id": "AAMkAGZmMTBkNmYwLTJjNjktNDE1NS05ZTA0LWM2NmVmNmM2NjIzNQAuAAAAAAA1Y8B/EL5oTJt9JNG3ClHGAQCHeWQkFedHR7fG98QQLjwkAAAAAAENAAA=",
        "ChangeKey": "AQAAAA=="
      },
      "Start": "2026-01-08T16:00:00+02:00",
      "End": "2026-01-08T18:00:00+02:00",
      "Subject": "Sisteme Wireless - TC I",
      "Sensitivity": "Normal",
      "FreeBusyType": "Busy",
      "CalendarItemType": "Occurrence",
      "Location": {
        "DisplayName": "UTCN - ETTI Observatorului 2 - Sala 410 (RO)",
        "PostalAddress": {
          "Street": null,
          "City": null,
          "State": null,
          "Country": null,
          "PostalCode": null,
          "PostOfficeBox": null,
          "Type": "Home",
          "LocationSource": "None"
        },
        "IdType": "Unknown",
        "LocationType": "Unknown"
      },
      "Charm": "None"
    },
    "source": "8813d675",
    "color": "#20c997"
  },
  {
    "start": "2026-01-08T18:00:00+02:00",
    "end": "2026-01-08T19:00:00+02:00",
    "title": "Proiect Cercetare",
    "location": "",
    "raw": {
      "__type": "CalendarItem:#Exchange",
      "ItemId": {
        "__type": "ItemId:#Exchange",
        "ChangeKey": "DwAAABYAAACHeWQkFedHR7fG98QQLjwkAAC1lNjX",
        "Id": "AAMkAGZmMTBkNmYwLTJjNjktNDE1NS05ZTA0LWM2NmVmNmM2NjIzNQFRAAgI3k5I3dxAAEYAAAAANWPAfxC+aEybfSTRtwpRxgcAh3lkJBXnR0e3xvfEEC48JAAAAAABDQAAh3lkJBXnR0e3xvfEEC48JAAAtXobwgAAEA=="
      },
      "ParentFolderId": {
        "__type": "FolderId:#Exchange",
        "Id": "AAMkAGZmMTBkNmYwLTJjNjktNDE1NS05ZTA0LWM2NmVmNmM2NjIzNQAuAAAAAAA1Y8B/EL5oTJt9JNG3ClHGAQCHeWQkFedHR7fG98QQLjwkAAAAAAENAAA=",
        "ChangeKey": "AQAAAA=="
      },
      "Start": "2026-01-08T18:00:00+02:00",
      "End": "2026-01-08T19:00:00+02:00",
      "Subject": "Proiect cercetare - TC I",
      "Sensitivity": "Normal",
      "FreeBusyType": "Busy",
      "CalendarItemType": "Occurrence",
      "Location": {
        "DisplayName": "",
        "PostalAddress": {
          "Street": null,
          "City": null,
          "State": null,
          "Country": null,
          "PostalCode": null,
          "PostOfficeBox": null,
          "Type": "Home",
          "LocationSource": "None"
        },
        "IdType": "Unknown",
        "LocationType": "Unknown"
      },
      "Charm": "None"
    },
    "source": "8813d675",
    "color": "#20c997"
  },
  {
    "start": "2026-01-12T10:00:00+02:00",
    "end": "2026-01-12T16:00:00+02:00",
    "title": "Radiocomunicații Celulare (l)",
    "location": "UTCN - ETTI Observatorului 2 - Sala 410 (RO)",
    "raw": {
      "__type": "CalendarItem:#Exchange",
      "ItemId": {
        "__type": "ItemId:#Exchange",
        "ChangeKey": "DwAAABYAAACHeWQkFedHR7fG98QQLjwkAAC1lNis",
        "Id": "AAMkAGZmMTBkNmYwLTJjNjktNDE1NS05ZTA0LWM2NmVmNmM2NjIzNQFRAAgI3lFth4NAAEYAAAAANWPAfxC+aEybfSTRtwpRxgcAh3lkJBXnR0e3xvfEEC48JAAAAAABDQAAh3lkJBXnR0e3xvfEEC48JAAAtXobvAAAEA=="
      },
      "ParentFolderId": {
        "__type": "FolderId:#Exchange",
        "Id": "AAMkAGZmMTBkNmYwLTJjNjktNDE1NS05ZTA0LWM2NmVmNmM2NjIzNQAuAAAAAAA1Y8B/EL5oTJt9JNG3ClHGAQCHeWQkFedHR7fG98QQLjwkAAAAAAENAAA=",
        "ChangeKey": "AQAAAA=="
      },
      "Start": "2026-01-12T10:00:00+02:00",
      "End": "2026-01-12T16:00:00+02:00",
      "Subject": "Radiocomunicații Celulare (L) - an IV TST-RO",
      "Sensitivity": "Normal",
      "FreeBusyType": "Busy",
      "CalendarItemType": "Occurrence",
      "Location": {
        "DisplayName": "UTCN - ETTI Observatorului 2 - Sala 410 (RO)",
        "PostalAddress": {
          "Street": null,
          "City": null,
          "State": null,
          "Country": null,
          "PostalCode": null,
          "PostOfficeBox": null,
          "Type": "Home",
          "LocationSource": "None"
        },
        "IdType": "Unknown",
        "LocationType": "Unknown"
      },
      "Charm": "None"
    },
    "source": "8813d675",
    "color": "#20c997"
  },
  {
    "start": "2026-01-12T14:00:00+02:00",
    "end": "2026-01-12T16:00:00+02:00",
    "title": "Rcc",
    "location": "",
    "raw": {
      "__type": "CalendarItem:#Exchange",
      "ItemId": {
        "__type": "ItemId:#Exchange",
        "ChangeKey": "DwAAABYAAACHeWQkFedHR7fG98QQLjwkAAC1lNhG",
        "Id": "AAMkAGZmMTBkNmYwLTJjNjktNDE1NS05ZTA0LWM2NmVmNmM2NjIzNQFRAAgI3lFth4NAAEYAAAAANWPAfxC+aEybfSTRtwpRxgcAh3lkJBXnR0e3xvfEEC48JAAAAAABDQAAh3lkJBXnR0e3xvfEEC48JAAAtXobugAAEA=="
      },
      "ParentFolderId": {
        "__type": "FolderId:#Exchange",
        "Id": "AAMkAGZmMTBkNmYwLTJjNjktNDE1NS05ZTA0LWM2NmVmNmM2NjIzNQAuAAAAAAA1Y8B/EL5oTJt9JNG3ClHGAQCHeWQkFedHR7fG98QQLjwkAAAAAAENAAA=",
        "ChangeKey": "AQAAAA=="
      },
      "Start": "2026-01-12T14:00:00+02:00",
      "End": "2026-01-12T16:00:00+02:00",
      "Subject": "RCC - 2242-2",
      "Sensitivity": "Normal",
      "FreeBusyType": "Busy",
      "CalendarItemType": "Occurrence",
      "Location": {
        "DisplayName": "",
        "PostalAddress": {
          "Street": null,
          "City": null,
          "State": null,
          "Country": null,
          "PostalCode": null,
          "PostOfficeBox": null,
          "Type": "Home",
          "LocationSource": "None"
        },
        "IdType": "Unknown",
        "LocationType": "Unknown"
      },
      "Charm": "None"
    },
    "source": "8813d675",
    "color": "#20c997"
  },
  {
    "start": "2026-01-13T08:00:00+02:00",
    "end": "2026-01-13T14:00:00+02:00",
    "title": "Sisteme De Comunicații (l)",
    "location": "UTCN - ETTI Observatorului 2 - Sala 410 (RO)",
    "raw": {
      "__type": "CalendarItem:#Exchange",
      "ItemId": {
        "__type": "ItemId:#Exchange",
        "ChangeKey": "DwAAABYAAACHeWQkFedHR7fG98QQLjwkAAC1lNim",
        "Id": "AAMkAGZmMTBkNmYwLTJjNjktNDE1NS05ZTA0LWM2NmVmNmM2NjIzNQFRAAgI3lI2se0AAEYAAAAANWPAfxC+aEybfSTRtwpRxgcAh3lkJBXnR0e3xvfEEC48JAAAAAABDQAAh3lkJBXnR0e3xvfEEC48JAAAtXobuwAAEA=="
      },
      "ParentFolderId": {
        "__type": "FolderId:#Exchange",
        "Id": "AAMkAGZmMTBkNmYwLTJjNjktNDE1NS05ZTA0LWM2NmVmNmM2NjIzNQAuAAAAAAA1Y8B/EL5oTJt9JNG3ClHGAQCHeWQkFedHR7fG98QQLjwkAAAAAAENAAA=",
        "ChangeKey": "AQAAAA=="
      },
      "Start": "2026-01-13T08:00:00+02:00",
      "End": "2026-01-13T14:00:00+02:00",
      "Subject": "Sisteme de comunicații (L) - an III IEDEEE ",
      "Sensitivity": "Normal",
      "FreeBusyType": "Busy",
      "CalendarItemType": "Occurrence",
      "Location": {
        "DisplayName": "UTCN - ETTI Observatorului 2 - Sala 410 (RO)",
        "PostalAddress": {
          "Street": null,
          "City": null,
          "State": null,
          "Country": null,
          "PostalCode": null,
          "PostOfficeBox": null,
          "Type": "Home",
          "LocationSource": "None"
        },
        "IdType": "Unknown",
        "LocationType": "Unknown"
      },
      "Charm": "None"
    },
    "source": "8813d675",
    "color": "#20c997"
  },
  {
    "start": "2026-01-14T10:00:00+02:00",
    "end": "2026-01-14T12:00:00+02:00",
    "title": "Sisteme De Comunicații",
    "location": "UTCN - ETTI Observatorului 2 - Sala 410 (RO)",
    "raw": {
      "__type": "CalendarItem:#Exchange",
      "ItemId": {
        "__type": "ItemId:#Exchange",
        "ChangeKey": "DwAAABYAAACHeWQkFedHR7fG98QQLjwkAAC1lNi0",
        "Id": "AAMkAGZmMTBkNmYwLTJjNjktNDE1NS05ZTA0LWM2NmVmNmM2NjIzNQFRAAgI3lL/3FbAAEYAAAAANWPAfxC+aEybfSTRtwpRxgcAh3lkJBXnR0e3xvfEEC48JAAAAAABDQAAh3lkJBXnR0e3xvfEEC48JAAAtXobvgAAEA=="
      },
      "ParentFolderId": {
        "__type": "FolderId:#Exchange",
        "Id": "AAMkAGZmMTBkNmYwLTJjNjktNDE1NS05ZTA0LWM2NmVmNmM2NjIzNQAuAAAAAAA1Y8B/EL5oTJt9JNG3ClHGAQCHeWQkFedHR7fG98QQLjwkAAAAAAENAAA=",
        "ChangeKey": "AQAAAA=="
      },
      "Start": "2026-01-14T10:00:00+02:00",
      "End": "2026-01-14T12:00:00+02:00",
      "Subject": "Sisteme de comunicații (P) - an III IEDEEE",
      "Sensitivity": "Normal",
      "FreeBusyType": "Busy",
      "CalendarItemType": "Occurrence",
      "Location": {
        "DisplayName": "UTCN - ETTI Observatorului 2 - Sala 410 (RO)",
        "PostalAddress": {
          "Street": null,
          "City": null,
          "State": null,
          "Country": null,
          "PostalCode": null,
          "PostOfficeBox": null,
          "Type": "Home",
          "LocationSource": "None"
        },
        "IdType": "Unknown",
        "LocationType": "Unknown"
      },
      "Charm": "None"
    },
    "source": "8813d675",
    "color": "#20c997"
  },
  {
    "start": "2026-01-14T17:00:00+02:00",
    "end": "2026-01-14T19:00:00+02:00",
    "title": "Proiectarea Rețelelor Radio",
    "location": "UTCN - ETTI Observatorului 2 - Sala 410 (RO)",
    "raw": {
      "__type": "CalendarItem:#Exchange",
      "ItemId": {
        "__type": "ItemId:#Exchange",
        "ChangeKey": "DwAAABYAAACHeWQkFedHR7fG98QQLjwkAAC1lNjs",
        "Id": "AAMkAGZmMTBkNmYwLTJjNjktNDE1NS05ZTA0LWM2NmVmNmM2NjIzNQFRAAgI3lL/3FbAAEYAAAAANWPAfxC+aEybfSTRtwpRxgcAh3lkJBXnR0e3xvfEEC48JAAAAAABDQAAh3lkJBXnR0e3xvfEEC48JAAAtXobwwAAEA=="
      },
      "ParentFolderId": {
        "__type": "FolderId:#Exchange",
        "Id": "AAMkAGZmMTBkNmYwLTJjNjktNDE1NS05ZTA0LWM2NmVmNmM2NjIzNQAuAAAAAAA1Y8B/EL5oTJt9JNG3ClHGAQCHeWQkFedHR7fG98QQLjwkAAAAAAENAAA=",
        "ChangeKey": "AQAAAA=="
      },
      "Start": "2026-01-14T17:00:00+02:00",
      "End": "2026-01-14T19:00:00+02:00",
      "Subject": "Proiectarea rețelelor radio - TC II",
      "Sensitivity": "Normal",
      "FreeBusyType": "Busy",
      "CalendarItemType": "Occurrence",
      "Location": {
        "DisplayName": "UTCN - ETTI Observatorului 2 - Sala 410 (RO)",
        "PostalAddress": {
          "Street": null,
          "City": null,
          "State": null,
          "Country": null,
          "PostalCode": null,
          "PostOfficeBox": null,
          "Type": "Home",
          "LocationSource": "None"
        },
        "IdType": "Unknown",
        "LocationType": "Unknown"
      },
      "Charm": "None"
    },
    "source": "8813d675",
    "color": "#20c997"
  },
  {
    "start": "2026-01-15T10:00:00+02:00",
    "end": "2026-01-15T14:00:00+02:00",
    "title": "Cellular Radiocommunications",
    "location": "UTCN - ETTI Observatorului 2 - Sala 410 (RO)",
    "raw": {
      "__type": "CalendarItem:#Exchange",
      "ItemId": {
        "__type": "ItemId:#Exchange",
        "ChangeKey": "DwAAABYAAACHeWQkFedHR7fG98QQLjwkAAC1lNi/",
        "Id": "AAMkAGZmMTBkNmYwLTJjNjktNDE1NS05ZTA0LWM2NmVmNmM2NjIzNQFRAAgI3lPJBsCAAEYAAAAANWPAfxC+aEybfSTRtwpRxgcAh3lkJBXnR0e3xvfEEC48JAAAAAABDQAAh3lkJBXnR0e3xvfEEC48JAAAtXobvwAAEA=="
      },
      "ParentFolderId": {
        "__type": "FolderId:#Exchange",
        "Id": "AAMkAGZmMTBkNmYwLTJjNjktNDE1NS05ZTA0LWM2NmVmNmM2NjIzNQAuAAAAAAA1Y8B/EL5oTJt9JNG3ClHGAQCHeWQkFedHR7fG98QQLjwkAAAAAAENAAA=",
        "ChangeKey": "AQAAAA=="
      },
      "Start": "2026-01-15T10:00:00+02:00",
      "End": "2026-01-15T14:00:00+02:00",
      "Subject": "Cellular Radiocommunications - IV TST-ENG",
      "Sensitivity": "Normal",
      "FreeBusyType": "Busy",
      "CalendarItemType": "Occurrence",
      "Location": {
        "DisplayName": "UTCN - ETTI Observatorului 2 - Sala 410 (RO)",
        "PostalAddress": {
          "Street": null,
          "City": null,
          "State": null,
          "Country": null,
          "PostalCode": null,
          "PostOfficeBox": null,
          "Type": "Home",
          "LocationSource": "None"
        },
        "IdType": "Unknown",
        "LocationType": "Unknown"
      },
      "Charm": "None"
    },
    "source": "8813d675",
    "color": "#20c997"
  },
  {
    "start": "2026-01-15T14:00:00+02:00",
    "end": "2026-01-15T16:00:00+02:00",
    "title": "Iot Project",
    "location": "UTCN - ETTI Observatorului 2 - Sala 410 (RO)",
    "raw": {
      "__type": "CalendarItem:#Exchange",
      "ItemId": {
        "__type": "ItemId:#Exchange",
        "ChangeKey": "DwAAABYAAACHeWQkFedHR7fG98QQLjwkAAC1lNjH",
        "Id": "AAMkAGZmMTBkNmYwLTJjNjktNDE1NS05ZTA0LWM2NmVmNmM2NjIzNQFRAAgI3lPJBsCAAEYAAAAANWPAfxC+aEybfSTRtwpRxgcAh3lkJBXnR0e3xvfEEC48JAAAAAABDQAAh3lkJBXnR0e3xvfEEC48JAAAtXobwAAAEA=="
      },
      "ParentFolderId": {
        "__type": "FolderId:#Exchange",
        "Id": "AAMkAGZmMTBkNmYwLTJjNjktNDE1NS05ZTA0LWM2NmVmNmM2NjIzNQAuAAAAAAA1Y8B/EL5oTJt9JNG3ClHGAQCHeWQkFedHR7fG98QQLjwkAAAAAAENAAA=",
        "ChangeKey": "AQAAAA=="
      },
      "Start": "2026-01-15T14:00:00+02:00",
      "End": "2026-01-15T16:00:00+02:00",
      "Subject": "IoT Project - IV TST-ENG",
      "Sensitivity": "Normal",
      "FreeBusyType": "Busy",
      "CalendarItemType": "Occurrence",
      "Location": {
        "DisplayName": "UTCN - ETTI Observatorului 2 - Sala 410 (RO)",
        "PostalAddress": {
          "Street": null,
          "City": null,
          "State": null,
          "Country": null,
          "PostalCode": null,
          "PostOfficeBox": null,
          "Type": "Home",
          "LocationSource": "None"
        },
        "IdType": "Unknown",
        "LocationType": "Unknown"
      },
      "Charm": "None"
    },
    "source": "8813d675",
    "color": "#20c997"
  },
  {
    "start": "2026-01-15T16:00:00+02:00",
    "end": "2026-01-15T18:00:00+02:00",
    "title": "Sisteme Wireless",
    "location": "UTCN - ETTI Observatorului 2 - Sala 410 (RO)",
    "raw": {
      "__type": "CalendarItem:#Exchange",
      "ItemId": {
        "__type": "ItemId:#Exchange",
        "ChangeKey": "DwAAABYAAACHeWQkFedHR7fG98QQLjwkAAC1lNjQ",
        "Id": "AAMkAGZmMTBkNmYwLTJjNjktNDE1NS05ZTA0LWM2NmVmNmM2NjIzNQFRAAgI3lPJBsCAAEYAAAAANWPAfxC+aEybfSTRtwpRxgcAh3lkJBXnR0e3xvfEEC48JAAAAAABDQAAh3lkJBXnR0e3xvfEEC48JAAAtXobwQAAEA=="
      },
      "ParentFolderId": {
        "__type": "FolderId:#Exchange",
        "Id": "AAMkAGZmMTBkNmYwLTJjNjktNDE1NS05ZTA0LWM2NmVmNmM2NjIzNQAuAAAAAAA1Y8B/EL5oTJt9JNG3ClHGAQCHeWQkFedHR7fG98QQLjwkAAAAAAENAAA=",
        "ChangeKey": "AQAAAA=="
      },
      "Start": "2026-01-15T16:00:00+02:00",
      "End": "2026-01-15T18:00:00+02:00",
      "Subject": "Sisteme Wireless - TC I",
      "Sensitivity": "Normal",
      "FreeBusyType": "Busy",
      "CalendarItemType": "Occurrence",
      "Location": {
        "DisplayName": "UTCN - ETTI Observatorului 2 - Sala 410 (RO)",
        "PostalAddress": {
          "Street": null,
          "City": null,
          "State": null,
          "Country": null,
          "PostalCode": null,
          "PostOfficeBox": null,
          "Type": "Home",
          "LocationSource": "None"
        },
        "IdType": "Unknown",
        "LocationType": "Unknown"
      },
      "Charm": "None"
    },
    "source": "8813d675",
    "color": "#20c997"
  },
  {
    "start": "2026-01-15T18:00:00+02:00",
    "end": "2026-01-15T19:00:00+02:00",
    "title": "Proiect Cercetare",
    "location": "",
    "raw": {
      "__type": "CalendarItem:#Exchange",
      "ItemId": {
        "__type": "ItemId:#Exchange",
        "ChangeKey": "DwAAABYAAACHeWQkFedHR7fG98QQLjwkAAC1lNjX",
        "Id": "AAMkAGZmMTBkNmYwLTJjNjktNDE1NS05ZTA0LWM2NmVmNmM2NjIzNQFRAAgI3lPJBsCAAEYAAAAANWPAfxC+aEybfSTRtwpRxgcAh3lkJBXnR0e3xvfEEC48JAAAAAABDQAAh3lkJBXnR0e3xvfEEC48JAAAtXobwgAAEA=="
      },
      "ParentFolderId": {
        "__type": "FolderId:#Exchange",
        "Id": "AAMkAGZmMTBkNmYwLTJjNjktNDE1NS05ZTA0LWM2NmVmNmM2NjIzNQAuAAAAAAA1Y8B/EL5oTJt9JNG3ClHGAQCHeWQkFedHR7fG98QQLjwkAAAAAAENAAA=",
        "ChangeKey": "AQAAAA=="
      },
      "Start": "2026-01-15T18:00:00+02:00",
      "End": "2026-01-15T19:00:00+02:00",
      "Subject": "Proiect cercetare - TC I",
      "Sensitivity": "Normal",
      "FreeBusyType": "Busy",
      "CalendarItemType": "Occurrence",
      "Location": {
        "DisplayName": "",
        "PostalAddress": {
          "Street": null,
          "City": null,
          "State": null,
          "Country": null,
          "PostalCode": null,
          "PostOfficeBox": null,
          "Type": "Home",
          "LocationSource": "None"
        },
        "IdType": "Unknown",
        "LocationType": "Unknown"
      },
      "Charm": "None"
    },
    "source": "8813d675",
    "color": "#20c997"
  }
]